{
  "project_info": {
    "project_number": "804223058216",
    "project_id": "mobile-5e0e9",
    "storage_bucket": "mobile-5e0e9.appspot.com"
  },
  "client": [
    {
      "client_info": {
        "mobilesdk_app_id": "1:804223058216:android:bfd35d18a12504c35e901d",
        "android_client_info": {
          "package_name": "com.example.tracking"
        }
      },
      "oauth_client": [
        {
          "client_id": "804223058216-5ia4743it3qh8jhblogsvr2p2ill1b3v.apps.googleusercontent.com",
          "client_type": 3
        }
      ],
      "api_key": [
        {
          "current_key": "AIzaSyDSLUaMD41bWa-1glWJij5lUiT5d5BKads"
        }
      ],
      "services": {
        "appinvite_service": {
          "other_platform_oauth_client": [
            {
              "client_id": "804223058216-5ia4743it3qh8jhblogsvr2p2ill1b3v.apps.googleusercontent.com",
              "client_type": 3
            }
          ]
        }
      }
    }
  ],
  "configuration_version": "1"
}